fastapi_dependency/__init__.py
fastapi_dependency/_main.py
fastapi_dependency/py.typed
fastapi_dependency-0.1.0.dist-info/METADATA
fastapi_dependency-0.1.0.dist-info/WHEEL
fastapi_dependency-0.1.0.dist-info/licenses/LICENSE
fastapi_dependency-0.1.0.dist-info/RECORD
